dutils/__init__.py
dutils/AWSViker.py
dutils/Color.py
dutils/Crypto.py
dutils/Database.py
dutils/Exceptions.py
dutils/ProgressBar.py
dutils/ProxySearch.py
dutils/Random.py
dutils/Reset.py
dutils/Reverse.py
dutils/Timer.py
dutils/Typer.py
dutils/UserAgent.py
sal_dutils-0.1.2.dist-info/WHEEL
sal_dutils-0.1.2.dist-info/METADATA
sal_dutils-0.1.2.dist-info/RECORD
