Metadata-Version: 2.1
Name: sal-dutils
Version: 0.1.2
Summary: 
Author: DesKaOne
Requires-Python: >=3.8,<4.0
Classifier: Programming Language :: Python :: 3
Classifier: Programming Language :: Python :: 3.8
Classifier: Programming Language :: Python :: 3.9
Classifier: Programming Language :: Python :: 3.10
Classifier: Programming Language :: Python :: 3.11
Requires-Dist: base58 (>=2.1.1,<3.0.0)
Requires-Dist: bs4 (>=0.0.1,<0.0.2)
Requires-Dist: colorama (>=0.4.6,<0.5.0)
Requires-Dist: pycryptodome (>=3.18.0,<4.0.0)
Requires-Dist: random-user-agent (>=1.0.1,<2.0.0)
Requires-Dist: requests[socks] (>=2.19.1,<2.30)
Requires-Dist: sqlalchemy (>=2.0.20,<3.0.0)
